mesa_viz_tornado/ModularVisualization.py
mesa_viz_tornado/TextVisualization.py
mesa_viz_tornado/UserParam.py
mesa_viz_tornado/__init__.py
mesa_viz_tornado/modules/BarChartVisualization.py
mesa_viz_tornado/modules/CanvasGridVisualization.py
mesa_viz_tornado/modules/ChartVisualization.py
mesa_viz_tornado/modules/HexGridVisualization.py
mesa_viz_tornado/modules/NetworkVisualization.py
mesa_viz_tornado/modules/PieChartVisualization.py
mesa_viz_tornado/modules/__init__.py
mesa_viz_tornado/templates/modular_template.html
mesa_viz_tornado/templates/css/visualization.css
mesa_viz_tornado/templates/external/bootstrap-5.1.3-dist/css/bootstrap-grid.css
mesa_viz_tornado/templates/external/bootstrap-5.1.3-dist/css/bootstrap-grid.css.map
mesa_viz_tornado/templates/external/bootstrap-5.1.3-dist/css/bootstrap-grid.min.css
mesa_viz_tornado/templates/external/bootstrap-5.1.3-dist/css/bootstrap-grid.min.css.map
mesa_viz_tornado/templates/external/bootstrap-5.1.3-dist/css/bootstrap-grid.rtl.css
mesa_viz_tornado/templates/external/bootstrap-5.1.3-dist/css/bootstrap-grid.rtl.css.map
mesa_viz_tornado/templates/external/bootstrap-5.1.3-dist/css/bootstrap-grid.rtl.min.css
mesa_viz_tornado/templates/external/bootstrap-5.1.3-dist/css/bootstrap-grid.rtl.min.css.map
mesa_viz_tornado/templates/external/bootstrap-5.1.3-dist/css/bootstrap-reboot.css
mesa_viz_tornado/templates/external/bootstrap-5.1.3-dist/css/bootstrap-reboot.css.map
mesa_viz_tornado/templates/external/bootstrap-5.1.3-dist/css/bootstrap-reboot.min.css
mesa_viz_tornado/templates/external/bootstrap-5.1.3-dist/css/bootstrap-reboot.min.css.map
mesa_viz_tornado/templates/external/bootstrap-5.1.3-dist/css/bootstrap-reboot.rtl.css
mesa_viz_tornado/templates/external/bootstrap-5.1.3-dist/css/bootstrap-reboot.rtl.css.map
mesa_viz_tornado/templates/external/bootstrap-5.1.3-dist/css/bootstrap-reboot.rtl.min.css
mesa_viz_tornado/templates/external/bootstrap-5.1.3-dist/css/bootstrap-reboot.rtl.min.css.map
Mesa_Viz_Tornado-0.1.3.dist-info/LICENSE
Mesa_Viz_Tornado-0.1.3.dist-info/METADATA
Mesa_Viz_Tornado-0.1.3.dist-info/WHEEL
Mesa_Viz_Tornado-0.1.3.dist-info/top_level.txt
Mesa_Viz_Tornado-0.1.3.dist-info/RECORD
