Metadata-Version: 2.1
Name: Mesa-Viz-Tornado
Version: 0.1.3
Summary: Tornado-based visualization framework for Mesa
Home-page: https://github.com/projectmesa/mesa-viz-tornado
Author: Project Mesa Team
Author-email: projectmesa@googlegroups.com
License: Apache 2.0
Keywords: agent based modeling model ABM simulation multi-agent
Requires-Python: >=3.8
License-File: LICENSE
Requires-Dist: tornado
Provides-Extra: dev
Requires-Dist: black; extra == "dev"
Requires-Dist: ruff==0.0.275; extra == "dev"
